[
    {
      "title": "Tech Conference 2024",
      "description": "A conference about the latest in tech innovations.",
      "eventDate": "2024-10-15T09:00:00Z",
      "organize": "Tech Innovators",
      "registeredUsers": ["6502fa5c85123a0f30e5df01", "6502fa5c85123a0f30e5df02"]
    },
    {
      "title": "Health and Wellness Expo",
      "description": "Explore the latest trends in health and wellness.",
      "eventDate": "2024-11-01T10:00:00Z",
      "organize": "Wellness Corp",
      "registeredUsers": ["6502fa5c85123a0f30e5df03", "6502fa5c85123a0f30e5df04"]
    },
    {
      "title": "Artificial Intelligence Summit",
      "description": "A summit focusing on AI and machine learning.",
      "eventDate": "2024-12-10T09:30:00Z",
      "organize": "AI Leaders",
      "registeredUsers": ["6502fa5c85123a0f30e5df05", "6502fa5c85123a0f30e5df06"]
    },
    {
      "title": "Blockchain for Business",
      "description": "An in-depth look at blockchain applications for enterprises.",
      "eventDate": "2024-10-22T08:30:00Z",
      "organize": "Blockchain Global",
      "registeredUsers": ["6502fa5c85123a0f30e5df07", "6502fa5c85123a0f30e5df08"]
    },
    {
      "title": "Startup Bootcamp",
      "description": "A weekend bootcamp for startup founders.",
      "eventDate": "2024-09-28T09:00:00Z",
      "organize": "Startup Lab",
      "registeredUsers": ["6502fa5c85123a0f30e5df09", "6502fa5c85123a0f30e5df10"]
    },
    {
      "title": "SaaS Product Demo Day",
      "description": "A showcase of the latest SaaS products.",
      "eventDate": "2024-10-18T11:00:00Z",
      "organize": "SaaS World",
      "registeredUsers": ["6502fa5c85123a0f30e5df11", "6502fa5c85123a0f30e5df12"]
    },
    {
      "title": "Coding Bootcamp Graduation",
      "description": "A ceremony celebrating the latest graduates of the coding bootcamp.",
      "eventDate": "2024-11-22T12:00:00Z",
      "organize": "Code Academy",
      "registeredUsers": ["6502fa5c85123a0f30e5df13", "6502fa5c85123a0f30e5df14"]
    },
    {
      "title": "Renewable Energy Expo",
      "description": "Explore innovations in renewable energy.",
      "eventDate": "2024-12-05T09:30:00Z",
      "organize": "Green Energy Summit",
      "registeredUsers": ["6502fa5c85123a0f30e5df15", "6502fa5c85123a0f30e5df16"]
    },
    {
      "title": "Smart Cities Conference",
      "description": "Discuss the future of smart cities around the world.",
      "eventDate": "2024-12-15T10:00:00Z",
      "organize": "Smart City Innovators",
      "registeredUsers": ["6502fa5c85123a0f30e5df17", "6502fa5c85123a0f30e5df18"]
    },
    {
      "title": "E-Commerce Strategy Summit",
      "description": "Tactics for scaling e-commerce businesses.",
      "eventDate": "2024-10-20T09:00:00Z",
      "organize": "E-Commerce Group",
      "registeredUsers": ["6502fa5c85123a0f30e5df19", "6502fa5c85123a0f30e5df20"]
    },
    {
      "title": "Digital Marketing Forum",
      "description": "Latest trends and strategies in digital marketing.",
      "eventDate": "2024-11-12T08:30:00Z",
      "organize": "Marketing Experts",
      "registeredUsers": ["6502fa5c85123a0f30e5df21", "6502fa5c85123a0f30e5df22"]
    },
    {
      "title": "Data Science Conference",
      "description": "A conference focused on data science and analytics.",
      "eventDate": "2024-09-30T09:30:00Z",
      "organize": "Data Science World",
      "registeredUsers": ["6502fa5c85123a0f30e5df23", "6502fa5c85123a0f30e5df24"]
    },
    {
      "title": "Virtual Reality Expo",
      "description": "Showcasing the latest advancements in virtual reality.",
      "eventDate": "2024-12-10T10:00:00Z",
      "organize": "VR Innovators",
      "registeredUsers": ["6502fa5c85123a0f30e5df25", "6502fa5c85123a0f30e5df26"]
    },
    {
      "title": "Cybersecurity Summit",
      "description": "Exploring the future of cybersecurity and data protection.",
      "eventDate": "2024-10-25T11:00:00Z",
      "organize": "Cyber Experts",
      "registeredUsers": ["6502fa5c85123a0f30e5df27", "6502fa5c85123a0f30e5df28"]
    },
    {
      "title": "Product Design Workshop",
      "description": "A hands-on workshop on modern product design.",
      "eventDate": "2024-09-18T08:00:00Z",
      "organize": "Design Labs",
      "registeredUsers": ["6502fa5c85123a0f30e5df29", "6502fa5c85123a0f30e5df30"]
    },
    {
      "title": "Mobile Development Conference",
      "description": "Discussing the latest trends in mobile app development.",
      "eventDate": "2024-11-08T09:00:00Z",
      "organize": "App Developers",
      "registeredUsers": ["6502fa5c85123a0f30e5df31", "6502fa5c85123a0f30e5df32"]
    },
    {
      "title": "Fintech Revolution Summit",
      "description": "A summit on the latest innovations in fintech.",
      "eventDate": "2024-10-05T10:30:00Z",
      "organize": "Fintech Global",
      "registeredUsers": ["6502fa5c85123a0f30e5df33", "6502fa5c85123a0f30e5df34"]
    },
    {
      "title": "Robotics Conference",
      "description": "Exploring the future of robotics and automation.",
      "eventDate": "2024-12-20T11:30:00Z",
      "organize": "Robotics Innovators",
      "registeredUsers": ["6502fa5c85123a0f30e5df35", "6502fa5c85123a0f30e5df36"]
    },
    {
      "title": "Wearable Tech Expo",
      "description": "A showcase of the latest wearable technologies.",
      "eventDate": "2024-11-22T08:00:00Z",
      "organize": "Tech Gear",
      "registeredUsers": ["6502fa5c85123a0f30e5df37", "6502fa5c85123a0f30e5df38"]
    },
    {
      "title": "Sustainability in Business",
      "description": "A conference focused on sustainable business practices.",
      "eventDate": "2024-10-30T09:30:00Z",
      "organize": "Sustainability World",
      "registeredUsers": ["6502fa5c85123a0f30e5df39", "6502fa5c85123a0f30e5df40"]
    },
    {
      "title": "Virtual Summit for Educators",
      "description": "Discussing the future of education in a digital world.",
      "eventDate": "2024-12-01T11:00:00Z",
      "organize": "EdTech Global",
      "registeredUsers": ["6502fa5c85123a0f30e5df41", "6502fa5c85123a0f30e5df42"]
    },
    {
      "title": "Gaming Industry Conference",
      "description": "Exploring the latest trends in the gaming industry.",
      "eventDate": "2024-09-25T09:00:00Z",
      "organize": "Gaming World",
      "registeredUsers": ["6502fa5c85123a0f30e5df43", "6502fa5c85123a0f30e5df44"]
    },
    {
      "title": "Mobile UX/UI Design Workshop",
      "description": "A hands-on workshop on mobile UX and UI design.",
      "eventDate": "2024-10-02T08:30:00Z",
      "organize": "Design Gurus",
      "registeredUsers": ["6502fa5c85123a0f30e5df45", "6502fa5c85123a0f30e5df46"]
    },
    {
      "title": "Internet of Things Expo",
      "description": "A showcase of the latest IoT technologies.",
      "eventDate": "2024-12-12T09:00:00Z",
      "organize": "IoT Leaders",
      "registeredUsers": ["6502fa5c85123a0f30e5df47", "6502fa5c85123a0f30e5df48"]
    }
  ]
